pyfloq/__init__.py
pyfloq/chart.py
pyfloq/cli.py
pyfloq/database_handler.py
pyfloq/timer.py
pyfloq/timestamps.py
pyfloq-0.1.0.dist-info/METADATA
pyfloq-0.1.0.dist-info/WHEEL
pyfloq-0.1.0.dist-info/entry_points.txt
pyfloq-0.1.0.dist-info/top_level.txt
pyfloq-0.1.0.dist-info/RECORD
