Metadata-Version: 2.4
Name: pyfloq
Version: 0.1.0
Summary: simple, effective time tracker with graph visualizations.
Requires-Dist: click~=8.3.1
Requires-Dist: plotext~=5.3.2
